msrx/__init__.py
msrx-0.3.data/scripts/msrx
msrx-0.3.dist-info/LICENSE.txt
msrx-0.3.dist-info/METADATA
msrx-0.3.dist-info/WHEEL
msrx-0.3.dist-info/top_level.txt
msrx-0.3.dist-info/RECORD
