Metadata-Version: 2.1
Name: msrx
Version: 0.3
Summary: Library and command line utils to use MSR605 magnetic card reader/writer
Home-page: https://github.com/oxplot/msrx
Author: Mansour Behabadi
Author-email: mansour@oxplot.com
Maintainer: Mansour Behabadi
Maintainer-email: mansour@oxplot.com
License: BSD
Classifier: Development Status :: 4 - Beta
Classifier: Environment :: Console
Classifier: Intended Audience :: Developers
Classifier: Intended Audience :: End Users/Desktop
Classifier: License :: OSI Approved :: BSD License
Classifier: Natural Language :: English
Classifier: Programming Language :: Python :: 2.7
Classifier: Programming Language :: Python :: 3.9
Classifier: Operating System :: POSIX :: Linux
Classifier: Topic :: Utilities
License-File: LICENSE.txt
